shop_sendcloud
